<?xml version="1.0"?>
<registry>
  <record name="plone.app.tiles">
    <value purge="false">
      <element>ps.plone.mlstiles.mosaic.development_collection</element>
      <element>ps.plone.mlstiles.mosaic.listing_collection</element>
      <element>ps.plone.mlstiles.mosaic.recent_listings</element>
      <element>ps.plone.mlstiles.mosaic.featured_listings</element>
      <element>ps.plone.mlstiles.mosaic.listing_search</element>
      <element>ps.plone.mlstiles.mosaic.listing_search_results</element>
    </value>
  </record>

  <records prefix="plone.app.mosaic.app_tiles.ps_plone_mlstiles_development_collection"
      interface="plone.app.mosaic.interfaces.ITile">
    <value key="name">ps.plone.mlstiles.mosaic.development_collection</value>
    <value key="label">MLS: Development Collection</value>
    <value key="category">applications</value>
    <value key="tile_type">app</value>
    <value key="default_value"></value>
    <value key="read_only">false</value>
    <value key="settings">true</value>
    <value key="favorite">false</value>
    <value key="rich_text">false</value>
    <value key="weight">110</value>
  </records>

  <records prefix="plone.app.mosaic.app_tiles.ps_plone_mlstiles_listing_collection"
      interface="plone.app.mosaic.interfaces.ITile">
    <value key="name">ps.plone.mlstiles.mosaic.listing_collection</value>
    <value key="label">MLS: Listing Collection</value>
    <value key="category">applications</value>
    <value key="tile_type">app</value>
    <value key="default_value"></value>
    <value key="read_only">false</value>
    <value key="settings">true</value>
    <value key="favorite">false</value>
    <value key="rich_text">false</value>
    <value key="weight">100</value>
  </records>

  <records prefix="plone.app.mosaic.app_tiles.ps_plone_mlstiles_recent_listings"
      interface="plone.app.mosaic.interfaces.ITile">
    <value key="name">ps.plone.mlstiles.mosaic.recent_listings</value>
    <value key="label">MLS: Recent Listings</value>
    <value key="category">applications</value>
    <value key="tile_type">app</value>
    <value key="default_value"></value>
    <value key="read_only">false</value>
    <value key="settings">true</value>
    <value key="favorite">false</value>
    <value key="rich_text">false</value>
    <value key="weight">101</value>
  </records>

  <records prefix="plone.app.mosaic.app_tiles.ps_plone_mlstiles_featured_listings"
      interface="plone.app.mosaic.interfaces.ITile">
    <value key="name">ps.plone.mlstiles.mosaic.featured_listings</value>
    <value key="label">MLS: Featured Listings</value>
    <value key="category">applications</value>
    <value key="tile_type">app</value>
    <value key="default_value"></value>
    <value key="read_only">false</value>
    <value key="settings">true</value>
    <value key="favorite">false</value>
    <value key="rich_text">false</value>
    <value key="weight">102</value>
  </records>

  <records prefix="plone.app.mosaic.app_tiles.ps_plone_mlstiles_listing_search"
      interface="plone.app.mosaic.interfaces.ITile">
    <value key="name">ps.plone.mlstiles.mosaic.listing_search</value>
    <value key="label">MLS: Listing Search</value>
    <value key="category">applications</value>
    <value key="tile_type">app</value>
    <value key="default_value"></value>
    <value key="read_only">false</value>
    <value key="settings">true</value>
    <value key="favorite">false</value>
    <value key="rich_text">false</value>
    <value key="weight">105</value>
  </records>

  <records prefix="plone.app.mosaic.app_tiles.ps_plone_mlstiles_listing_search_results"
      interface="plone.app.mosaic.interfaces.ITile">
    <value key="name">ps.plone.mlstiles.mosaic.listing_search_results</value>
    <value key="label">MLS: Listing Search Results</value>
    <value key="category">applications</value>
    <value key="tile_type">app</value>
    <value key="default_value"></value>
    <value key="read_only">false</value>
    <value key="settings">true</value>
    <value key="favorite">false</value>
    <value key="rich_text">false</value>
    <value key="weight">106</value>
  </records>
</registry>
